odoo/addons/product_catalog_stock/README.rst
odoo/addons/product_catalog_stock/__init__.py
odoo/addons/product_catalog_stock/__manifest__.py
odoo/addons/product_catalog_stock/i18n/it.po
odoo/addons/product_catalog_stock/i18n/nl.po
odoo/addons/product_catalog_stock/i18n/product_catalog_stock.pot
odoo/addons/product_catalog_stock/models/__init__.py
odoo/addons/product_catalog_stock/models/stock_picking.py
odoo/addons/product_catalog_stock/models/stock_picking_type.py
odoo/addons/product_catalog_stock/readme/CONTRIBUTORS.md
odoo/addons/product_catalog_stock/readme/DESCRIPTION.md
odoo/addons/product_catalog_stock/readme/USAGE.md
odoo/addons/product_catalog_stock/static/description/icon.png
odoo/addons/product_catalog_stock/static/description/index.html
odoo/addons/product_catalog_stock/static/src/components/product_catalog/kanban_controller.esm.js
odoo/addons/product_catalog_stock/static/src/components/product_catalog/order_line.esm.js
odoo/addons/product_catalog_stock/views/stock_picking_type_views.xml
odoo/addons/product_catalog_stock/views/stock_picking_views.xml
odoo_addon_product_catalog_stock-18.0.1.0.0.4.dist-info/METADATA
odoo_addon_product_catalog_stock-18.0.1.0.0.4.dist-info/WHEEL
odoo_addon_product_catalog_stock-18.0.1.0.0.4.dist-info/top_level.txt
odoo_addon_product_catalog_stock-18.0.1.0.0.4.dist-info/RECORD
